{"user":{"playlists":"0","playcount":"5591","gender":"n","name":"","subscriber":"1","url":"https:\/\/www.last.fm\/user\/KimNamjoon","country":"France","image":[{"size":"small","#text":"https:\/\/lastfm.freetls.fastly.net\/i\/u\/34s\/7f0fe23606bce61a5968eeb4bf1cc8b7.png"},{"size":"medium","#text":"https:\/\/lastfm.freetls.fastly.net\/i\/u\/64s\/7f0fe23606bce61a5968eeb4bf1cc8b7.png"},{"size":"large","#text":"https:\/\/lastfm.freetls.fastly.net\/i\/u\/174s\/7f0fe23606bce61a5968eeb4bf1cc8b7.png"},{"size":"extralarge","#text":"https:\/\/lastfm.freetls.fastly.net\/i\/u\/300x300\/7f0fe23606bce61a5968eeb4bf1cc8b7.png"}],"registered":{"unixtime":"1579044924","#text":1579044924},"type":"subscriber","age":"0","bootstrap":"0","realname":""}}
